README.md
setup.py
docums_git_revision_date_plugin/__init__.py
docums_git_revision_date_plugin/plugin.py
docums_git_revision_date_plugin/util.py
docums_git_revision_date_plugin.egg-info/PKG-INFO
docums_git_revision_date_plugin.egg-info/SOURCES.txt
docums_git_revision_date_plugin.egg-info/dependency_links.txt
docums_git_revision_date_plugin.egg-info/entry_points.txt
docums_git_revision_date_plugin.egg-info/requires.txt
docums_git_revision_date_plugin.egg-info/top_level.txt