Metadata-Version: 1.2
Name: docums-git-revision-date-plugin
Version: 1.0
Summary: Docums plugin for setting revision date from git per markdown file.
Home-page: https://github.com/khanhduy1407/docums-git-revision-date-plugin/
Author: NKDuy
Author-email: kn145660@gmail.com
License: MIT
Keywords: docums git meta yaml frontmatter
Platform: UNKNOWN
Requires-Python: >=3.4
